[
  {
    "track": "Running in the Night",
    "artist": "FM-84, Ollie Wride"
  },
  {
    "track": "Emergence",
    "artist": "ROOTIME"
  },
  {
    "track": "Pressure - Alesso Radio Edit",
    "artist": "Nadia Ali, Starkillers, Alex Kenji, Alesso"
  },
  {
    "track": "Forget About You - Sunrise Mix",
    "artist": "Rammor"
  },
  {
    "track": "alive",
    "artist": "Troy Ogletree"
  },
  {
    "track": "TOO HARD.",
    "artist": "Kesha"
  },
  {
    "track": "miserable all the time",
    "artist": "Rad Cat"
  },
  {
    "track": "Easy - Radio Edit",
    "artist": "Mat Zo, Porter Robinson"
  },
  {
    "track": "Wild Ride",
    "artist": "KSHMR"
  },
  {
    "track": "Girls Like You",
    "artist": "Sofia Camara"
  },
  {
    "track": "fragments of us",
    "artist": "GhostDragon"
  },
  {
    "track": "Lose Your Love",
    "artist": "Keerthin, Andrew A"
  },
  {
    "track": "GLOW (feat. Au/Ra)",
    "artist": "San Holo, Au/Ra"
  },
  {
    "track": "GLASS EYES",
    "artist": "jacket."
  },
  {
    "track": "When I Get There",
    "artist": "Big Wild"
  },
  {
    "track": "In Time",
    "artist": "Matteo Cole"
  },
  {
    "track": "Redefined (feat. Melanie Fontana & Novaspace) [Club Edit]",
    "artist": "tyDi, Melanie Fontana"
  },
  {
    "track": "Bad Match",
    "artist": "Dani Doucette"
  },
  {
    "track": "You're the One for Me - Digital Farm Animals Remix",
    "artist": "Great Good Fine Ok, Digital Farm Animals"
  },
  {
    "track": "Sunglasses",
    "artist": "Sagan, Sam Russell"
  },
  {
    "track": "Golden Remedy",
    "artist": "Feki, LANKS, Sloan Peterson"
  },
  {
    "track": "One More Time",
    "artist": "Daft Punk"
  },
  {
    "track": "Silver Lining",
    "artist": "Andrew Rayel"
  },
  {
    "track": "Under The Stars",
    "artist": "Walido"
  },
  {
    "track": "Kill You",
    "artist": "Daniella Spadini"
  },
  {
    "track": "I Don't Mind",
    "artist": "Particle House, Le June"
  },
  {
    "track": "where r u",
    "artist": "Kill Paris"
  },
  {
    "track": "Omen",
    "artist": "Ross Quinn, Punctual"
  },
  {
    "track": "kill me for always (feat. porter robinson)",
    "artist": "Michael Clifford, Porter Robinson"
  },
  {
    "track": "Infinity",
    "artist": "JOSS, Gryxx, Johnny Lo"
  }
]