[
  {
    "track": "Phoenix",
    "artist": "League of Legends, Cailin Russo, Chrissy Costanza"
  },
  {
    "track": "Shooting Stars",
    "artist": "Forester, Lincoln Jesser"
  },
  {
    "track": "Messy (From F1® The Movie)",
    "artist": "ROSÉ, F1 The Album"
  },
  {
    "track": "Claws",
    "artist": "Kim Petras"
  },
  {
    "track": "Mortals Funk Remix",
    "artist": "LXNGVX, Warriyo"
  },
  {
    "track": "Physical (feat. Troye Sivan)",
    "artist": "Dua Lipa, Troye Sivan"
  },
  {
    "track": "My Sins",
    "artist": "ADENZA"
  },
  {
    "track": "Shut Down",
    "artist": "BLACKPINK"
  },
  {
    "track": "Memory Reboot",
    "artist": "VØJ, Narvent"
  },
  {
    "track": "Water",
    "artist": "Tyla"
  },
  {
    "track": "怪物",
    "artist": "YOASOBI"
  },
  {
    "track": "Animals",
    "artist": "Maroon 5"
  },
  {
    "track": "Club Can't Handle Me (feat. David Guetta)",
    "artist": "Flo Rida, David Guetta"
  },
  {
    "track": "I Want It That Way",
    "artist": "Backstreet Boys"
  },
  {
    "track": "Moonshine",
    "artist": "Alan Walker, Elley Duhé"
  },
  {
    "track": "Rise Up",
    "artist": "TheFatRat"
  },
  {
    "track": "BACK TO LIFE",
    "artist": "Angrybaby"
  },
  {
    "track": "On & On",
    "artist": "Cartoon, Jéja, Daniel Levi"
  },
  {
    "track": "Light Switch",
    "artist": "Charlie Puth"
  },
  {
    "track": "Dreams pt. II",
    "artist": "Lost Sky, Sara Skinner"
  },
  {
    "track": "Colors",
    "artist": "Halsey"
  },
  {
    "track": "AVANGARD - Slowed",
    "artist": "LONOWN"
  },
  {
    "track": "Best Song Ever",
    "artist": "One Direction"
  },
  {
    "track": "Lullaby",
    "artist": "Brvski, Catching Sunrises, Afro Queen"
  },
  {
    "track": "Hung Up",
    "artist": "Madonna"
  },
  {
    "track": "The Days - NOTION Remix",
    "artist": "Chrystal, NOTION"
  },
  {
    "track": "YOU AND I",
    "artist": "Golowko, Alicee"
  },
  {
    "track": "telepatía",
    "artist": "Kali Uchis"
  },
  {
    "track": "In My Mind",
    "artist": "Dynoro, Gigi D'Agostino"
  }
]